{
  "customers": [
    {
      "id": "c1",
      "name": "Donnie Brasco",
      "purchases": [
        {
          "id": "p1",
          "testid": "donnie-brasco",
          "amount": "30.00",
          "date": "2022-05-01"
        },
        {
          "id": "p2",
          "amount": "51.00",
          "date": "2022-05-15"
        },
        {
          "id": "p3",
          "amount": "80.00",
          "date": "2022-07-01"
        },
        {
          "id": "p4",
          "amount": "110.00",
          "date": "2022-07-14"
        },
        {
          "id": "p5",
          "amount": "84.00",
          "date": "2022-07-03"
        },
        {
          "id": "p6",
          "amount": "144.00",
          "date": "2022-07-18"
        }
      ]
    },
    {
      "id": "c2",
      "name": "Henry Hill",
      "purchases": [
        {
          "id": "p1",
          "amount": "35.00",
          "date": "2022-05-02"
        },
        {
          "id": "p2",
          "amount": "65.00",
          "date": "2022-05-16"
        },
        {
          "id": "p3",
          "amount": "88.00",
          "date": "2022-07-02"
        },
        {
          "id": "p4",
          "amount": "111.00",
          "date": "2022-07-17"
        },
        {
          "id": "p5",
          "amount": "72.00",
          "date": "2022-07-06"
        },
        {
          "id": "p6",
          "amount": "123.00",
          "date": "2022-07-16"
        }
      ]
    },
    {
      "id": "c3",
      "name": "Moe Green",
      "purchases": [
        {
          "id": "p1",
          "amount": "37.00",
          "date": "2022-05-12"
        },
        {
          "id": "p2",
          "amount": "78.00",
          "date": "2022-05-20"
        },
        {
          "id": "p3",
          "amount": "92.00",
          "date": "2022-07-12"
        },
        {
          "id": "p4",
          "amount": "129.00",
          "date": "2022-07-27"
        },
        {
          "id": "p5",
          "amount": "22.00",
          "date": "2022-07-13"
        },
        {
          "id": "p6",
          "amount": "99.00",
          "date": "2022-07-21"
        }
      ]
    }
  ]
}
